seika/GetAngle.py
seika/__init__.py
seika-0.0.1.dist-info/DESCRIPTION.rst
seika-0.0.1.dist-info/METADATA
seika-0.0.1.dist-info/metadata.json
seika-0.0.1.dist-info/RECORD
seika-0.0.1.dist-info/top_level.txt
seika-0.0.1.dist-info/WHEEL
