Metadata-Version: 2.0
Name: seika
Version: 0.0.1
Summary: Software for running SEIKA sensors
Home-page: http://www.seika.de/
Author: SEIKA Mikrosystemtechnik GmbH
Author-email: seika@seika.com
License: UNKNOWN
Platform: UNKNOWN
Classifier: Programming Language :: Python :: 3
Classifier: License :: OSI Approved :: MIT License
Classifier: Operating System :: OS Independent
